{
  "region": "cervical",
  "title": "Cervical Region",
  "source_file": "Cervical Region.docx",
  "extracted_at": "2026-02-04T03:56:23.890Z",
  "version": "2.0.0",
  "conditions": [
    {
      "name": "Cervical Disc Herniation",
      "id": "cervical_disc_herniation",
      "entry_criteria": [],
      "questions": [
        {
          "id": "cervical_q1",
          "questionText": "Where is your pain worse?",
          "category": "location",
          "inputType": "select",
          "options": [
            {
              "value": "Neck",
              "nextQuestionId": "cervical_q2",
              "effects": {
                "increase_likelihood": [],
                "decrease_likelihood": []
              }
            },
            {
              "value": "Neck-Arm",
              "nextQuestionId": "cervical_q2",
              "effects": {
                "increase_likelihood": [],
                "decrease_likelihood": []
              }
            }
          ],
          "metadata": {
            "source_line": 2
          }
        },
        {
          "id": "cervical_q2",
          "questionText": "How did the pain begin?",
          "category": "onset",
          "inputType": "select",
          "options": [
            {
              "value": "Sudden",
              "nextQuestionId": "cervical_q3",
              "effects": {
                "increase_likelihood": [],
                "decrease_likelihood": []
              }
            },
            {
              "value": "Gradual",
              "nextQuestionId": "cervical_q15",
              "branchTo": [
                "cervical spondylosis"
              ],
              "effects": {
                "rule_out": [
                  "cervical spondylosis"
                ],
                "increase_likelihood": [],
                "decrease_likelihood": []
              }
            }
          ],
          "metadata": {
            "source_line": 5
          }
        },
        {
          "id": "cervical_q3",
          "questionText": "Age (Below 40 years)?",
          "category": "demographic",
          "inputType": "select",
          "options": [
            {
              "value": "Sex",
              "nextQuestionId": "cervical_q4",
              "effects": {
                "increase_likelihood": [],
                "decrease_likelihood": []
              },
              "metadata": {
                "notes": "Male"
              }
            }
          ],
          "metadata": {
            "source_line": 8
          }
        },
        {
          "id": "cervical_q4",
          "questionText": "Do you feel numbness in any form?",
          "category": "neurological",
          "inputType": "select",
          "options": [
            {
              "value": "Yes",
              "nextQuestionId": "cervical_q5",
              "effects": {
                "increase_likelihood": [],
                "decrease_likelihood": []
              }
            },
            {
              "value": "No",
              "nextQuestionId": "cervical_q5",
              "effects": {
                "increase_likelihood": [],
                "decrease_likelihood": []
              }
            }
          ],
          "metadata": {
            "source_line": 10
          }
        },
        {
          "id": "cervical_q5",
          "questionText": "Which of these movements currently aggravates your pain?",
          "category": "general",
          "inputType": "select",
          "options": [
            {
              "value": "Flexion",
              "nextQuestionId": "cervical_q6",
              "effects": {
                "increase_likelihood": [],
                "decrease_likelihood": []
              },
              "metadata": {
                "notes": "Bending neck forward"
              }
            },
            {
              "value": "Extension",
              "nextQuestionId": "cervical_q6",
              "effects": {
                "increase_likelihood": [],
                "decrease_likelihood": []
              },
              "metadata": {
                "notes": "Bending neck backward"
              }
            }
          ],
          "metadata": {
            "source_line": 13
          }
        },
        {
          "id": "cervical_q6",
          "questionText": "What movements relieve your pain?",
          "category": "general",
          "inputType": "select",
          "options": [
            {
              "value": "Flexion",
              "nextQuestionId": "cervical_q7",
              "effects": {
                "increase_likelihood": [],
                "decrease_likelihood": []
              },
              "metadata": {
                "notes": "Bending neck forward"
              }
            },
            {
              "value": "Extension",
              "nextQuestionId": "cervical_q7",
              "effects": {
                "increase_likelihood": [],
                "decrease_likelihood": []
              },
              "metadata": {
                "notes": "Bending neck backward"
              }
            }
          ],
          "metadata": {
            "source_line": 16
          }
        },
        {
          "id": "cervical_q7",
          "questionText": "Do you feel more pain when you move your neck?",
          "category": "temporal",
          "inputType": "select",
          "options": [
            {
              "value": "Yes",
              "nextQuestionId": "cervical_q8",
              "effects": {
                "increase_likelihood": [],
                "decrease_likelihood": []
              }
            },
            {
              "value": "No",
              "nextQuestionId": "cervical_q8",
              "effects": {
                "increase_likelihood": [],
                "decrease_likelihood": []
              }
            }
          ],
          "metadata": {
            "source_line": 19
          }
        },
        {
          "id": "cervical_q8",
          "questionText": "Do you experience some stiffness in your neck?",
          "category": "stiffness",
          "inputType": "select",
          "options": [
            {
              "value": "Yes",
              "nextQuestionId": "cervical_q9",
              "effects": {
                "increase_likelihood": [],
                "decrease_likelihood": []
              }
            },
            {
              "value": "No",
              "nextQuestionId": "cervical_q9",
              "effects": {
                "increase_likelihood": [],
                "decrease_likelihood": []
              }
            }
          ],
          "metadata": {
            "source_line": 22
          }
        },
        {
          "id": "cervical_q9",
          "questionText": "Does the pain increase with coughing, sneezing, straining or laughing?",
          "category": "general",
          "inputType": "select",
          "options": [
            {
              "value": "Yes",
              "nextQuestionId": "cervical_q10",
              "branchTo": [
                "cervical myelopathy"
              ],
              "effects": {
                "rule_out": [
                  "cervical myelopathy"
                ],
                "increase_likelihood": [],
                "decrease_likelihood": []
              }
            },
            {
              "value": "No",
              "nextQuestionId": "cervical_q10",
              "effects": {
                "increase_likelihood": [],
                "decrease_likelihood": []
              }
            }
          ],
          "metadata": {
            "source_line": 25
          }
        },
        {
          "id": "cervical_q10",
          "questionText": "Do you have any restrictions with movement around your neck?",
          "category": "general",
          "inputType": "select",
          "options": [
            {
              "value": "Yes",
              "nextQuestionId": "cervical_q11",
              "branchTo": [
                "cervical stenosis"
              ],
              "effects": {
                "rule_out": [
                  "cervical stenosis"
                ],
                "increase_likelihood": [],
                "decrease_likelihood": []
              }
            },
            {
              "value": "No",
              "nextQuestionId": "cervical_q11",
              "effects": {
                "increase_likelihood": [],
                "decrease_likelihood": []
              }
            }
          ],
          "metadata": {
            "source_line": 28
          }
        },
        {
          "id": "cervical_q11",
          "questionText": "Do you also have any pain around your lower back, buttocks, thigh or legs?",
          "category": "general",
          "inputType": "select",
          "options": [
            {
              "value": "Yes",
              "nextQuestionId": "cervical_q12",
              "effects": {
                "increase_likelihood": [],
                "decrease_likelihood": []
              }
            },
            {
              "value": "No",
              "nextQuestionId": "cervical_q12",
              "effects": {
                "increase_likelihood": [],
                "decrease_likelihood": []
              }
            }
          ],
          "metadata": {
            "source_line": 31
          }
        },
        {
          "id": "cervical_q12",
          "questionText": "Does the pain wake you up at night?",
          "category": "temporal",
          "inputType": "select",
          "options": [
            {
              "value": "Yes",
              "nextQuestionId": "cervical_q13",
              "effects": {
                "increase_likelihood": [],
                "decrease_likelihood": []
              }
            },
            {
              "value": "No",
              "nextQuestionId": "cervical_q13",
              "effects": {
                "increase_likelihood": [],
                "decrease_likelihood": []
              }
            }
          ],
          "metadata": {
            "source_line": 34
          }
        },
        {
          "id": "cervical_q13",
          "questionText": "Do you feel any form of muscle weakness?",
          "category": "neurological",
          "inputType": "select",
          "options": [
            {
              "value": "Yes",
              "nextQuestionId": "cervical_q14",
              "effects": {
                "increase_likelihood": [],
                "decrease_likelihood": []
              }
            },
            {
              "value": "No",
              "nextQuestionId": "cervical_q14",
              "effects": {
                "increase_likelihood": [],
                "decrease_likelihood": []
              }
            }
          ],
          "metadata": {
            "source_line": 37
          }
        },
        {
          "id": "cervical_q14",
          "questionText": "Do you experience impaired sensations in your arm and forearm?",
          "category": "general",
          "inputType": "select",
          "options": [
            {
              "value": "Yes",
              "nextQuestionId": null,
              "effects": {
                "increase_likelihood": [],
                "decrease_likelihood": []
              },
              "isTerminal": true
            },
            {
              "value": "No",
              "nextQuestionId": null,
              "effects": {
                "increase_likelihood": [],
                "decrease_likelihood": []
              },
              "isTerminal": true
            }
          ],
          "metadata": {
            "source_line": 40
          }
        }
      ],
      "metadata": {
        "source_line": 1
      },
      "recommended_tests": [],
      "confirmation_methods": [
        "Radiographic confirmation"
      ],
      "observations": [
        "Check if cervical rotation on the affected side is less than 60 degrees.",
        "TESTS:",
        "Spurling’s Test (Maximal Cervical Compression and Foraminal Compression Test): The neck is placed in extension, lateral flexion, and axial compression. The test is positive if pain is present and radiates to the arm.",
        "Cervical Distraction Test: The patient lies supine and the neck is positioned comfortably.  The examiner places hand around the patient’s mastoid process. The examiner then slightly flexes the patient’s neck and pull the head towards your torso.Test is positive if the symptoms reduces or is eliminated with traction.",
        "MRI test"
      ]
    },
    {
      "name": "Cervical Spondylosis",
      "id": "cervical_spondylosis",
      "entry_criteria": [],
      "questions": [
        {
          "id": "cervical_q15",
          "questionText": "Where is your pain worse?",
          "category": "location",
          "inputType": "select",
          "options": [
            {
              "value": "Back-Buttocks",
              "nextQuestionId": "cervical_q16",
              "effects": {
                "increase_likelihood": [],
                "decrease_likelihood": []
              }
            },
            {
              "value": "Leg",
              "nextQuestionId": "cervical_q16",
              "effects": {
                "increase_likelihood": [],
                "decrease_likelihood": []
              }
            },
            {
              "value": "Neck",
              "nextQuestionId": "cervical_q16",
              "effects": {
                "increase_likelihood": [],
                "decrease_likelihood": []
              }
            },
            {
              "value": "Neck-Arm",
              "nextQuestionId": "cervical_q16",
              "effects": {
                "increase_likelihood": [],
                "decrease_likelihood": []
              }
            }
          ],
          "metadata": {
            "source_line": 51
          }
        },
        {
          "id": "cervical_q16",
          "questionText": "How did the pain begin?",
          "category": "onset",
          "inputType": "select",
          "options": [
            {
              "value": "Sudden",
              "nextQuestionId": "cervical_q17",
              "effects": {
                "increase_likelihood": [],
                "decrease_likelihood": []
              }
            },
            {
              "value": "Gradual",
              "nextQuestionId": "cervical_q17",
              "effects": {
                "increase_likelihood": [],
                "decrease_likelihood": []
              }
            }
          ],
          "metadata": {
            "source_line": 56
          }
        },
        {
          "id": "cervical_q17",
          "questionText": "Age (Above 40 years)?",
          "category": "demographic",
          "inputType": "select",
          "options": [
            {
              "value": "Sex",
              "nextQuestionId": "cervical_q18",
              "effects": {
                "increase_likelihood": [],
                "decrease_likelihood": []
              },
              "metadata": {
                "notes": "Female"
              }
            }
          ],
          "metadata": {
            "source_line": 59
          }
        },
        {
          "id": "cervical_q18",
          "questionText": "Do you feel numbness in any form?",
          "category": "neurological",
          "inputType": "select",
          "options": [
            {
              "value": "Yes",
              "nextQuestionId": "cervical_q19",
              "effects": {
                "increase_likelihood": [],
                "decrease_likelihood": []
              }
            },
            {
              "value": "No",
              "nextQuestionId": "cervical_q19",
              "effects": {
                "increase_likelihood": [],
                "decrease_likelihood": []
              }
            }
          ],
          "metadata": {
            "source_line": 61
          }
        },
        {
          "id": "cervical_q19",
          "questionText": "Which of these movements currently aggravates your pain?",
          "category": "general",
          "inputType": "select",
          "options": [
            {
              "value": "Flexion",
              "nextQuestionId": "cervical_q20",
              "effects": {
                "increase_likelihood": [],
                "decrease_likelihood": []
              },
              "metadata": {
                "notes": "Bending neck forward"
              }
            },
            {
              "value": "Extension",
              "nextQuestionId": "cervical_q20",
              "effects": {
                "increase_likelihood": [],
                "decrease_likelihood": []
              },
              "metadata": {
                "notes": "Bending neck backward"
              }
            }
          ],
          "metadata": {
            "source_line": 64
          }
        },
        {
          "id": "cervical_q20",
          "questionText": "What movements relieve your pain?",
          "category": "general",
          "inputType": "select",
          "options": [
            {
              "value": "Flexion",
              "nextQuestionId": "cervical_q21",
              "effects": {
                "increase_likelihood": [],
                "decrease_likelihood": []
              },
              "metadata": {
                "notes": "Bending neck forward"
              }
            },
            {
              "value": "Extension",
              "nextQuestionId": "cervical_q21",
              "effects": {
                "increase_likelihood": [],
                "decrease_likelihood": []
              },
              "metadata": {
                "notes": "Bending neck backward"
              }
            }
          ],
          "metadata": {
            "source_line": 67
          }
        },
        {
          "id": "cervical_q21",
          "questionText": "Do you feel more pain when you move your neck?",
          "category": "temporal",
          "inputType": "select",
          "options": [
            {
              "value": "Yes",
              "nextQuestionId": "cervical_q22",
              "effects": {
                "increase_likelihood": [],
                "decrease_likelihood": []
              }
            },
            {
              "value": "No",
              "nextQuestionId": "cervical_q22",
              "effects": {
                "increase_likelihood": [],
                "decrease_likelihood": []
              }
            }
          ],
          "metadata": {
            "source_line": 70
          }
        },
        {
          "id": "cervical_q22",
          "questionText": "Does the pain relieve you with rest?",
          "category": "general",
          "inputType": "select",
          "options": [
            {
              "value": "Yes",
              "nextQuestionId": "cervical_q23",
              "effects": {
                "increase_likelihood": [],
                "decrease_likelihood": []
              }
            },
            {
              "value": "No",
              "nextQuestionId": "cervical_q23",
              "effects": {
                "increase_likelihood": [],
                "decrease_likelihood": []
              }
            }
          ],
          "metadata": {
            "source_line": 73
          }
        },
        {
          "id": "cervical_q23",
          "questionText": "Does the pain increase with coughing, sneezing, straining, or laughing?",
          "category": "general",
          "inputType": "select",
          "options": [
            {
              "value": "Yes",
              "nextQuestionId": "cervical_q24",
              "effects": {
                "increase_likelihood": [],
                "decrease_likelihood": []
              }
            },
            {
              "value": "No",
              "nextQuestionId": "cervical_q24",
              "effects": {
                "increase_likelihood": [],
                "decrease_likelihood": []
              }
            }
          ],
          "metadata": {
            "source_line": 76
          }
        },
        {
          "id": "cervical_q24",
          "questionText": "Do you experience intermittent neck pain and shoulder pain?",
          "category": "general",
          "inputType": "select",
          "options": [
            {
              "value": "Yes",
              "nextQuestionId": "cervical_q25",
              "effects": {
                "increase_likelihood": [],
                "decrease_likelihood": []
              }
            },
            {
              "value": "No",
              "nextQuestionId": "cervical_q25",
              "effects": {
                "increase_likelihood": [],
                "decrease_likelihood": []
              }
            }
          ],
          "metadata": {
            "source_line": 79
          }
        },
        {
          "id": "cervical_q25",
          "questionText": "Do you have any restrictions with movement around your neck?",
          "category": "general",
          "inputType": "select",
          "options": [
            {
              "value": "Yes",
              "nextQuestionId": "cervical_q26",
              "branchTo": [
                "cervical stenosis"
              ],
              "effects": {
                "rule_out": [
                  "cervical stenosis"
                ],
                "increase_likelihood": [],
                "decrease_likelihood": []
              }
            },
            {
              "value": "No",
              "nextQuestionId": "cervical_q26",
              "effects": {
                "increase_likelihood": [],
                "decrease_likelihood": []
              }
            }
          ],
          "metadata": {
            "source_line": 82
          }
        },
        {
          "id": "cervical_q26",
          "questionText": "Do you also have any pain around your lower back, buttocks, thigh, or legs?",
          "category": "general",
          "inputType": "select",
          "options": [
            {
              "value": "Yes",
              "nextQuestionId": "cervical_q27",
              "effects": {
                "increase_likelihood": [],
                "decrease_likelihood": []
              }
            },
            {
              "value": "No",
              "nextQuestionId": "cervical_q27",
              "effects": {
                "increase_likelihood": [],
                "decrease_likelihood": []
              }
            }
          ],
          "metadata": {
            "source_line": 85
          }
        },
        {
          "id": "cervical_q27",
          "questionText": "Does the pain wake you up at night?",
          "category": "temporal",
          "inputType": "select",
          "options": [
            {
              "value": "Yes",
              "nextQuestionId": "cervical_q28",
              "effects": {
                "increase_likelihood": [],
                "decrease_likelihood": []
              }
            },
            {
              "value": "No",
              "nextQuestionId": "cervical_q28",
              "effects": {
                "increase_likelihood": [],
                "decrease_likelihood": []
              }
            }
          ],
          "metadata": {
            "source_line": 88
          }
        },
        {
          "id": "cervical_q28",
          "questionText": "Do you feel any form of muscle weakness?",
          "category": "neurological",
          "inputType": "select",
          "options": [
            {
              "value": "Yes",
              "nextQuestionId": "cervical_q29",
              "effects": {
                "increase_likelihood": [],
                "decrease_likelihood": []
              }
            },
            {
              "value": "No",
              "nextQuestionId": "cervical_q29",
              "effects": {
                "increase_likelihood": [],
                "decrease_likelihood": []
              }
            }
          ],
          "metadata": {
            "source_line": 91
          }
        },
        {
          "id": "cervical_q29",
          "questionText": "Do you experience muscle spasms?",
          "category": "general",
          "inputType": "select",
          "options": [
            {
              "value": "Yes",
              "nextQuestionId": null,
              "effects": {
                "increase_likelihood": [],
                "decrease_likelihood": []
              },
              "isTerminal": true
            },
            {
              "value": "No",
              "nextQuestionId": null,
              "effects": {
                "increase_likelihood": [],
                "decrease_likelihood": []
              },
              "isTerminal": true
            }
          ],
          "metadata": {
            "source_line": 94
          }
        }
      ],
      "metadata": {
        "source_line": 50
      },
      "recommended_tests": [
        "Spurling’s Test (Maximal Cervical Compression and Foraminal Compression Test): The neck is placed in extension, lateral flexion, and axial compression. The test is positive if pain is present and radiates to the arm."
      ],
      "confirmation_methods": [
        "Radiographic confirmation: check for loss of normal cervical lordosis, and degeneration."
      ],
      "observations": []
    }
  ]
}